__init__.py
compare_checker.py
flatter.py
shape_print.py
striper.py
forme-1.0.0.dist-info/LICENSE
forme-1.0.0.dist-info/METADATA
forme-1.0.0.dist-info/WHEEL
forme-1.0.0.dist-info/top_level.txt
forme-1.0.0.dist-info/RECORD
