Metadata-Version: 2.1
Name: forme
Version: 1.0.0
Summary: The package that I use it useful
Author-email: Bahk InSung <insung.park123@gmail.com>
License: Copyright 2022. Bahk InSung.        
Project-URL: Homepage, https://github.com/insung3511/forme
Project-URL: Bug Tracker, https://github.com/insung3511/forme/issues
Classifier: Programming Language :: Python :: 3
Classifier: License :: OSI Approved :: MIT License
Classifier: Operating System :: OS Independent
Requires-Python: >=3.8.0
License-File: LICENSE
